cleese_stim/__init__.py
cleese_stim/cleese.py
cleese_stim/engines/__init__.py
cleese_stim/engines/engine.py
cleese_stim/engines/face_warp/__init__.py
cleese_stim/engines/face_warp/face_warp.py
cleese_stim/engines/phase_vocoder/__init__.py
cleese_stim/engines/phase_vocoder/audio_engine.py
cleese_stim/engines/phase_vocoder/bpf.py
cleese_stim/engines/phase_vocoder/phase_vocoder.py
cleese_stim/engines/phase_vocoder/utils.py
cleese_stim/third_party/__init__.py
cleese_stim/third_party/audio_processing.py
cleese_stim/third_party/yin.py
cleese_stim/third_party/mls/__init__.py
cleese_stim/third_party/mls/demo.py
cleese_stim/third_party/mls/img_utils.py
cleese_stim/third_party/mls/img_utils_pytorch.py
cleese_stim/third_party/mls/interp_torch.py
cleese_stim-2.3.4.dist-info/LICENSE
cleese_stim-2.3.4.dist-info/METADATA
cleese_stim-2.3.4.dist-info/WHEEL
cleese_stim-2.3.4.dist-info/top_level.txt
cleese_stim-2.3.4.dist-info/RECORD
