Metadata-Version: 2.1
Name: cleese_stim
Version: 2.3.4
Summary: Audio and visual stimuli generation tool
Home-page: https://github.com/neuro-team-femto/cleese
License: MIT License
Project-URL: Bug Tracker, https://github.com/neuro-team-femto/cleese/issues
Keywords: sound manipulation,phase vocoder
Classifier: Intended Audience :: Science/Research
Classifier: License :: OSI Approved :: MIT License
Classifier: Programming Language :: Python :: 3
Classifier: Topic :: Multimedia :: Sound/Audio :: Speech
Classifier: Topic :: Scientific/Engineering :: Image Processing
Classifier: Topic :: Sociology
License-File: LICENSE
Requires-Dist: mediapipe
Requires-Dist: numpy
Requires-Dist: scipy
Requires-Dist: tomli
Requires-Dist: msvc-runtime ; platform_system == "Windows"
